astrodom/__init__.py
astrodom/__main__.py
astrodom/blinkDialog.py
astrodom/dashboardTreeModel.py
astrodom/dashboardTreeView.py
astrodom/fileMonitorWidget.py
astrodom/fileOperationDialog.py
astrodom/file_monitor.py
astrodom/fits_header_table.py
astrodom/loadSettings.py
astrodom/logHandler.py
astrodom/measure_stars.py
astrodom/plotDialog.py
astrodom/previewAndDataWidget.py
astrodom/projectDialog.py
astrodom/projectsArchiveWidget.py
astrodom/settingsDialog.py
astrodom/starAnalysisDialog.py
astrodom/syncImages.py
astrodom/syncProgressDialog.py
astrodom/utils.py
astrodom/viewDelegates.py
astrodom/rsc/CITATION.rst
astrodom/rsc/settings.json
astrodom/rsc/docs/PIvsAD.png
astrodom/rsc/docs/astrodomWF.png
astrodom/rsc/docs/astrodom_worflow.png
astrodom/rsc/docs/charts.png
astrodom/rsc/docs/file_operations.png
astrodom/rsc/docs/home.png
astrodom/rsc/docs/main_window.png
astrodom/rsc/docs/projects.png
astrodom/rsc/docs/selected_star_zoom.png
astrodom/rsc/docs/star_analysis.png
astrodom/rsc/docs/star_profile.png
astrodom/rsc/docs/sync_confirmation.png
astrodom/rsc/docs/thresholds.png
astrodom/rsc/gui/mainWindow.ui
astrodom/rsc/gui/mainWindow_ui.py
astrodom/rsc/gui/projects.ui
astrodom/rsc/gui/starAnalisys.ui
astrodom/rsc/icons/application-monitor.png
astrodom/rsc/icons/astrodom.png
astrodom/rsc/icons/chart-up.png
astrodom/rsc/icons/cross.png
astrodom/rsc/icons/database--plus.png
astrodom/rsc/icons/database-import.png
astrodom/rsc/icons/database-insert.png
astrodom/rsc/icons/disk.png
astrodom/rsc/icons/external.png
astrodom/rsc/icons/firstquarter.png
astrodom/rsc/icons/folder-open.png
astrodom/rsc/icons/folder-search-result.png
astrodom/rsc/icons/fullmoon.png
astrodom/rsc/icons/gear.png
astrodom/rsc/icons/keyword.png
astrodom/rsc/icons/lastquarter.png
astrodom/rsc/icons/newmoon.png
astrodom/rsc/icons/star.png
astrodom/rsc/icons/sync.png
astrodom/rsc/icons/waningcrescent.png
astrodom/rsc/icons/waninggibbous.png
astrodom/rsc/icons/waxingcrescent.png
astrodom-2.1.37.dist-info/METADATA
astrodom-2.1.37.dist-info/WHEEL
astrodom-2.1.37.dist-info/top_level.txt
astrodom-2.1.37.dist-info/RECORD
