Metadata-Version: 2.2
Name: astrodom
Version: 2.1.37
Summary: Astroimaging Catalogue Software
Home-page: https://github.com/fenriques/AstroDom
Author: Ferrante Enriques
Author-email: ferrante.enriques@gmail.com
License: MIT
Classifier: Development Status :: 4 - Beta
Classifier: Environment :: X11 Applications :: Qt
Classifier: Environment :: Other Environment
Classifier: Programming Language :: Python :: 3 :: Only
Classifier: Operating System :: Microsoft :: Windows :: Windows 10
Classifier: Operating System :: POSIX :: Linux
Classifier: Intended Audience :: Education
Classifier: Intended Audience :: Science/Research
Classifier: Topic :: Scientific/Engineering :: Astronomy
Classifier: License :: OSI Approved :: Apache Software License
Classifier: Natural Language :: English
Requires-Python: >=3.12
Requires-Dist: astropy
Requires-Dist: ephem
Requires-Dist: matplotlib
Requires-Dist: numpy
Requires-Dist: pandas
Requires-Dist: PyQt6
Requires-Dist: photutils
Requires-Dist: pyqtgraph
Requires-Dist: importlib_resources
Requires-Dist: watchdog
Dynamic: author
Dynamic: author-email
Dynamic: classifier
Dynamic: description
Dynamic: description-content-type
Dynamic: home-page
Dynamic: license
Dynamic: requires-dist
Dynamic: requires-python
Dynamic: summary
